ingenii_quantum/__init__.py
ingenii_quantum/examples/hybrid_2D_CNN.ipynb
ingenii_quantum/examples/hybrid_3D_CNN.ipynb
ingenii_quantum/examples/hybrid_fully_connected.ipynb
ingenii_quantum/examples/quantum_edge_detection.ipynb
ingenii_quantum/examples/quantum_fusion_model.ipynb
ingenii_quantum/examples/quantum_inspired_filter.ipynb
ingenii_quantum/examples/__pycache__/edge_detection.cpython-311.pyc
ingenii_quantum/examples/__pycache__/filters.cpython-311.pyc
ingenii_quantum/examples/__pycache__/layers.cpython-311.pyc
ingenii_quantum/examples/__pycache__/layers_Pennylane.cpython-39.pyc
ingenii_quantum/examples/__pycache__/qinsp_filter.cpython-311.pyc
ingenii_quantum/examples/__pycache__/utils.cpython-311.pyc
ingenii_quantum/examples/data/core_test.csv
ingenii_quantum/examples/data/core_test_fc10.npy
ingenii_quantum/examples/data/core_test_fc6.npy
ingenii_quantum/examples/data/data_reader.py
ingenii_quantum/examples/data/img_util.py
ingenii_quantum/examples/data/pbdbind2016_core_test_3dnn.csv
ingenii_quantum/examples/data/pdbbind2016_core_test.hdf
ingenii_quantum/examples/data/refined_train.csv
ingenii_quantum/examples/data/refined_train_fc10.npy
ingenii_quantum/examples/data/refined_train_fc6.npy
ingenii_quantum/examples/data/refined_val.csv
ingenii_quantum/examples/data/refined_val_fc10.npy
ingenii_quantum/examples/data/refined_val_fc6.npy
ingenii_quantum/examples/data/ultrasound_image.png
ingenii_quantum/examples/data/__pycache__/data_reader.cpython-311.pyc
ingenii_quantum/examples/data/__pycache__/img_util.cpython-311.pyc
ingenii_quantum/examples/images/HybridCNN.png
ingenii_quantum/examples/images/HybridCNN2.png
ingenii_quantum/examples/images/HybridCNN2D.png
ingenii_quantum/examples/images/HybridCNN2Db.png
ingenii_quantum/examples/images/edge-detection.png
ingenii_quantum/examples/images/fusion_model.png
ingenii_quantum/hybrid_networks/__init__.py
ingenii_quantum/hybrid_networks/edge_detection.py
ingenii_quantum/hybrid_networks/filters.py
ingenii_quantum_hybrid_networks-0.3.2.dist-info/METADATA
ingenii_quantum_hybrid_networks-0.3.2.dist-info/WHEEL
ingenii_quantum_hybrid_networks-0.3.2.dist-info/dependency_links.txt
ingenii_quantum_hybrid_networks-0.3.2.dist-info/top_level.txt
ingenii_quantum_hybrid_networks-0.3.2.dist-info/RECORD
