Metadata-Version: 2.1
Name: ingenii_quantum_hybrid_networks
Version: 0.3.2
Summary: Hybrid quantum-classical neural networks for 2D and 3D image processing
Home-page: https://github.com/ingenii-solutions/ingenii-quantum-hybrid-networks
Author: Ingenii
Author-email: laia@ingenii.dev
Classifier: Programming Language :: Python :: 3
Classifier: License :: OSI Approved :: Mozilla Public License 2.0 (MPL 2.0)
Classifier: Operating System :: OS Independent
Requires-Dist: qiskit>=1.2
Requires-Dist: qiskit-aer>=0.15
Requires-Dist: qiskit-ibm-runtime>=0.31
Requires-Dist: scikit-learn>=1.5
Requires-Dist: scipy>=1.14
Requires-Dist: h5py>=3.12
Requires-Dist: matplotlib>=3.6.1
Requires-Dist: pylatexenc>=2.10
Requires-Dist: torch>=2.1
Requires-Dist: torchaudio>=0.13.0
Requires-Dist: torchvision>=0.14.0
Requires-Dist: torch-geometric>=2.1.0.post1
Requires-Dist: pennylane>=0.38.0
Requires-Dist: tensorflow>=2.18.0
Requires-Dist: numpy>=1.26
